<PAMDataset>
  <Metadata>
    <MDI key="DESCRIPTION"></MDI>
    <MDI key="LATITUDE">40</MDI>
    <MDI key="LINEAR_UNIT">Meters</MDI>
  </Metadata>
  <PAMRasterBand band="1">
    <Description>Elevation</Description>
    <Histograms>
      <HistItem>
        <HistMin>34,6715</HistMin>
        <HistMax>692,3285</HistMax>
        <BucketCount>1000</BucketCount>
        <IncludeOutOfRange>0</IncludeOutOfRange>
        <Approximate>0</Approximate>
        <HistCounts>1|0|0|2|0|1|1|0|5|9|0|11|12|0|17|12|0|20|14|0|8|17|0|11|9|0|13|15|0|29|25|0|25|18|0|32|29|0|26|0|29|20|0|27|18|0|24|23|0|20|24|0|25|23|0|20|34|0|17|23|0|21|18|0|36|23|0|24|572|0|73|95|0|167|0|109|113|0|94|107|0|81|86|0|80|73|0|82|68|0|80|81|0|78|88|0|69|84|0|74|82|0|74|82|0|74|76|0|79|71|0|85|0|85|69|0|79|69|0|89|85|0|83|80|0|90|75|0|76|63|0|72|92|0|70|87|0|78|75|0|86|73|0|78|67|0|61|87|0|60|0|77|84|0|86|87|0|88|89|0|88|75|0|76|87|0|76|81|0|70|86|0|79|68|0|58|76|0|80|83|0|59|92|0|83|0|86|74|0|88|84|0|73|91|0|84|81|0|83|93|0|80|98|0|78|87|0|102|81|0|84|92|0|97|99|0|96|115|0|93|116|0|84|0|104|91|0|87|91|0|102|119|0|108|104|0|120|113|0|111|151|0|121|140|0|133|151|0|150|173|0|129|152|0|129|123|0|130|113|0|102|0|123|107|0|129|131|0|109|94|0|128|100|0|99|94|0|114|144|0|149|196|0|161|129|0|139|121|0|114|105|0|109|97|0|116|0|110|92|0|95|98|0|123|120|0|136|124|0|112|98|0|105|115|0|108|110|0|124|101|0|126|133|0|163|205|0|174|149|0|150|169|0|145|0|135|123|0|127|187|0|162|177|0|178|164|0|179|149|0|171|205|0|182|176|0|168|172|0|170|164|0|183|168|0|153|169|0|135|158|0|134|0|136|117|0|144|108|0|125|115|0|112|99|0|114|99|0|121|116|0|133|114|0|114|129|0|103|110|0|103|88|0|85|94|0|99|0|90|89|0|93|97|0|115|110|0|120|133|0|135|119|0|121|125|0|136|172|0|168|168|0|172|167|0|206|205|0|175|184|0|194|210|0|220|0|176|172|0|181|186|0|155|144|0|126|129|0|106|99|0|86|71|0|98|80|0|65|71|0|69|73|0|75|80|0|68|70|0|51|73|0|54|0|59|52|0|55|59|0|59|52|0|57|47|0|49|53|0|55|56|0|50|52|0|47|41|0|45|43|0|54|46|0|53|47|0|35|0|40|47|0|51|39|0|44|55|0|46|44|0|49|44|0|54|44|0|52|51|0|42|57|0|61|60|0|53|41|0|50|51|0|44|43|0|42|0|42|31|0|43|52|0|35|48|0|41|38|0|53|51|0|45|43|0|42|43|0|43|50|0|43|37|0|42|30|0|44|40|0|49|40|0|40|0|55|35|0|45|46|0|38|34|0|33|47|0|49|40|0|38|41|0|36|38|0|34|45|0|45|40|0|43|35|0|34|38|0|36|0|37|34|0|34|31|0|37|35|0|28|26|0|28|32|0|19|18|0|29|22|0|27|20|0|22|35|0|19|24|0|29|31|0|22|28|0|32|0|32|21|0|18|16|0|21|14|0|28|26|0|17|23|0|24|29|0|23|24|0|27|19|0|26|17|0|33|23|0|22|26|0|20|30|0|28|0|27|23|0|21|28|0|24|30|0|20|32|0|26|25|0|24|20|0|27|25|0|23|37|0|27|16|0|26|17|0|26|19|0|19|0|23|28|0|19|21|0|18|27|0|18|23|0|17|23|0|19|20|0|28|17|0|18|25|0|24|21|0|24|18|0|22|21|0|24|16|0|23|0|21|17|0|17|15|0|16|21|0|24|13|0|19|28|0|19|23|0|24|25|0|13|21|0|16|16|0|22|19|0|15|15|0|14|15|0|14|0|23|18|0|17|20|0|20|7|0|20|19|0|14|17|0|13|10|0|14|13|0|17|12|0|16|22|0|14|9|0|20|15|0|6|0|19|12|0|20|12|0|12|14|0|9|16|0|10|14|0|9|13|0|11|13|0|12|18|0|13|16|0|9|14|0|11|11|0|10|17|0|7|0|10|9|0|17|8|0|9|12|0|5|12|0|8|10|0|5|11|0|13|5|0|7|7|0|5|5|0|5|4|0|4|8|0|4|11|0|4|0|4|3|0|3|6|0|4|3|0|2|5|0|1|2|0|2|3|0|1|5|0|1|3|0|4|1|0|1|1|0|0|1|0|2|0|0|0|0|2|0|0|1|2|0|2|2|0|0|1|0|2|0|0|1|0|0|0|0|0|1|0|0|2|0|0|0|1|0|0|2|0|2</HistCounts>
      </HistItem>
    </Histograms>
    <Metadata>
      <MDI key="ELEVATION_FILE">Elevation.asc</MDI>
      <MDI key="ELEVATION_MAX">692</MDI>
      <MDI key="ELEVATION_MIN">35</MDI>
      <MDI key="ELEVATION_NUM_CLASSES">-1</MDI>
      <MDI key="ELEVATION_UNIT">0</MDI>
      <MDI key="ELEVATION_UNIT_NAME">Meters</MDI>
      <MDI key="STATISTICS_MAXIMUM">692</MDI>
      <MDI key="STATISTICS_MEAN">270,80410667334</MDI>
      <MDI key="STATISTICS_MINIMUM">35</MDI>
      <MDI key="STATISTICS_STDDEV">124,52087502374</MDI>
    </Metadata>
  </PAMRasterBand>
  <PAMRasterBand band="2">
    <Description>Slope</Description>
    <Histograms>
      <HistItem>
        <HistMin>-10004,0165</HistMin>
        <HistMax>39,0165</HistMax>
        <BucketCount>1000</BucketCount>
        <IncludeOutOfRange>0</IncludeOutOfRange>
        <Approximate>0</Approximate>
        <HistCounts>812|0|0|0|0|0|0|0|0|0|0|0|0|0|0|0|0|0|0|0|0|0|0|0|0|0|0|0|0|0|0|0|0|0|0|0|0|0|0|0|0|0|0|0|0|0|0|0|0|0|0|0|0|0|0|0|0|0|0|0|0|0|0|0|0|0|0|0|0|0|0|0|0|0|0|0|0|0|0|0|0|0|0|0|0|0|0|0|0|0|0|0|0|0|0|0|0|0|0|0|0|0|0|0|0|0|0|0|0|0|0|0|0|0|0|0|0|0|0|0|0|0|0|0|0|0|0|0|0|0|0|0|0|0|0|0|0|0|0|0|0|0|0|0|0|0|0|0|0|0|0|0|0|0|0|0|0|0|0|0|0|0|0|0|0|0|0|0|0|0|0|0|0|0|0|0|0|0|0|0|0|0|0|0|0|0|0|0|0|0|0|0|0|0|0|0|0|0|0|0|0|0|0|0|0|0|0|0|0|0|0|0|0|0|0|0|0|0|0|0|0|0|0|0|0|0|0|0|0|0|0|0|0|0|0|0|0|0|0|0|0|0|0|0|0|0|0|0|0|0|0|0|0|0|0|0|0|0|0|0|0|0|0|0|0|0|0|0|0|0|0|0|0|0|0|0|0|0|0|0|0|0|0|0|0|0|0|0|0|0|0|0|0|0|0|0|0|0|0|0|0|0|0|0|0|0|0|0|0|0|0|0|0|0|0|0|0|0|0|0|0|0|0|0|0|0|0|0|0|0|0|0|0|0|0|0|0|0|0|0|0|0|0|0|0|0|0|0|0|0|0|0|0|0|0|0|0|0|0|0|0|0|0|0|0|0|0|0|0|0|0|0|0|0|0|0|0|0|0|0|0|0|0|0|0|0|0|0|0|0|0|0|0|0|0|0|0|0|0|0|0|0|0|0|0|0|0|0|0|0|0|0|0|0|0|0|0|0|0|0|0|0|0|0|0|0|0|0|0|0|0|0|0|0|0|0|0|0|0|0|0|0|0|0|0|0|0|0|0|0|0|0|0|0|0|0|0|0|0|0|0|0|0|0|0|0|0|0|0|0|0|0|0|0|0|0|0|0|0|0|0|0|0|0|0|0|0|0|0|0|0|0|0|0|0|0|0|0|0|0|0|0|0|0|0|0|0|0|0|0|0|0|0|0|0|0|0|0|0|0|0|0|0|0|0|0|0|0|0|0|0|0|0|0|0|0|0|0|0|0|0|0|0|0|0|0|0|0|0|0|0|0|0|0|0|0|0|0|0|0|0|0|0|0|0|0|0|0|0|0|0|0|0|0|0|0|0|0|0|0|0|0|0|0|0|0|0|0|0|0|0|0|0|0|0|0|0|0|0|0|0|0|0|0|0|0|0|0|0|0|0|0|0|0|0|0|0|0|0|0|0|0|0|0|0|0|0|0|0|0|0|0|0|0|0|0|0|0|0|0|0|0|0|0|0|0|0|0|0|0|0|0|0|0|0|0|0|0|0|0|0|0|0|0|0|0|0|0|0|0|0|0|0|0|0|0|0|0|0|0|0|0|0|0|0|0|0|0|0|0|0|0|0|0|0|0|0|0|0|0|0|0|0|0|0|0|0|0|0|0|0|0|0|0|0|0|0|0|0|0|0|0|0|0|0|0|0|0|0|0|0|0|0|0|0|0|0|0|0|0|0|0|0|0|0|0|0|0|0|0|0|0|0|0|0|0|0|0|0|0|0|0|0|0|0|0|0|0|0|0|0|0|0|0|0|0|0|0|0|0|0|0|0|0|0|0|0|0|0|0|0|0|0|0|0|0|0|0|0|0|0|0|0|0|0|0|0|0|0|0|0|0|0|0|0|0|0|0|0|0|0|0|0|0|0|0|0|0|0|0|0|0|0|0|0|0|0|0|0|0|0|0|0|0|0|0|0|0|0|0|0|0|0|0|0|0|0|0|0|0|0|0|0|0|0|0|0|0|0|0|0|0|0|0|0|0|0|0|0|0|0|0|0|0|0|0|0|0|0|0|0|0|0|0|0|0|0|0|0|0|0|0|0|0|0|0|0|0|0|0|0|0|0|0|0|0|0|0|0|0|0|0|0|0|0|0|0|0|0|0|0|0|0|0|0|0|0|0|0|0|0|0|0|0|0|0|0|0|0|0|0|0|0|0|0|0|0|0|0|0|0|0|0|0|0|0|0|0|0|0|0|0|0|0|0|0|0|0|0|0|0|0|0|0|0|0|0|0|0|0|0|0|0|0|0|0|31919|6511|664|29</HistCounts>
      </HistItem>
    </Histograms>
    <Metadata>
      <MDI key="SLOPE_FILE">Slope.asc</MDI>
      <MDI key="SLOPE_MAX">34</MDI>
      <MDI key="SLOPE_MIN">0</MDI>
      <MDI key="SLOPE_NUM_CLASSES">36</MDI>
      <MDI key="SLOPE_UNIT">0</MDI>
      <MDI key="SLOPE_UNIT_NAME">Degrees</MDI>
      <MDI key="STATISTICS_MAXIMUM">34</MDI>
      <MDI key="STATISTICS_MEAN">-198,86583197696</MDI>
      <MDI key="STATISTICS_MINIMUM">-9999</MDI>
      <MDI key="STATISTICS_STDDEV">1411,8756800438</MDI>
    </Metadata>
  </PAMRasterBand>
  <PAMRasterBand band="3">
    <Description>Aspect</Description>
    <Histograms>
      <HistItem>
        <HistMin>-10004,179</HistMin>
        <HistMax>364,179</HistMax>
        <BucketCount>1000</BucketCount>
        <IncludeOutOfRange>0</IncludeOutOfRange>
        <Approximate>0</Approximate>
        <HistCounts>1224|0|0|0|0|0|0|0|0|0|0|0|0|0|0|0|0|0|0|0|0|0|0|0|0|0|0|0|0|0|0|0|0|0|0|0|0|0|0|0|0|0|0|0|0|0|0|0|0|0|0|0|0|0|0|0|0|0|0|0|0|0|0|0|0|0|0|0|0|0|0|0|0|0|0|0|0|0|0|0|0|0|0|0|0|0|0|0|0|0|0|0|0|0|0|0|0|0|0|0|0|0|0|0|0|0|0|0|0|0|0|0|0|0|0|0|0|0|0|0|0|0|0|0|0|0|0|0|0|0|0|0|0|0|0|0|0|0|0|0|0|0|0|0|0|0|0|0|0|0|0|0|0|0|0|0|0|0|0|0|0|0|0|0|0|0|0|0|0|0|0|0|0|0|0|0|0|0|0|0|0|0|0|0|0|0|0|0|0|0|0|0|0|0|0|0|0|0|0|0|0|0|0|0|0|0|0|0|0|0|0|0|0|0|0|0|0|0|0|0|0|0|0|0|0|0|0|0|0|0|0|0|0|0|0|0|0|0|0|0|0|0|0|0|0|0|0|0|0|0|0|0|0|0|0|0|0|0|0|0|0|0|0|0|0|0|0|0|0|0|0|0|0|0|0|0|0|0|0|0|0|0|0|0|0|0|0|0|0|0|0|0|0|0|0|0|0|0|0|0|0|0|0|0|0|0|0|0|0|0|0|0|0|0|0|0|0|0|0|0|0|0|0|0|0|0|0|0|0|0|0|0|0|0|0|0|0|0|0|0|0|0|0|0|0|0|0|0|0|0|0|0|0|0|0|0|0|0|0|0|0|0|0|0|0|0|0|0|0|0|0|0|0|0|0|0|0|0|0|0|0|0|0|0|0|0|0|0|0|0|0|0|0|0|0|0|0|0|0|0|0|0|0|0|0|0|0|0|0|0|0|0|0|0|0|0|0|0|0|0|0|0|0|0|0|0|0|0|0|0|0|0|0|0|0|0|0|0|0|0|0|0|0|0|0|0|0|0|0|0|0|0|0|0|0|0|0|0|0|0|0|0|0|0|0|0|0|0|0|0|0|0|0|0|0|0|0|0|0|0|0|0|0|0|0|0|0|0|0|0|0|0|0|0|0|0|0|0|0|0|0|0|0|0|0|0|0|0|0|0|0|0|0|0|0|0|0|0|0|0|0|0|0|0|0|0|0|0|0|0|0|0|0|0|0|0|0|0|0|0|0|0|0|0|0|0|0|0|0|0|0|0|0|0|0|0|0|0|0|0|0|0|0|0|0|0|0|0|0|0|0|0|0|0|0|0|0|0|0|0|0|0|0|0|0|0|0|0|0|0|0|0|0|0|0|0|0|0|0|0|0|0|0|0|0|0|0|0|0|0|0|0|0|0|0|0|0|0|0|0|0|0|0|0|0|0|0|0|0|0|0|0|0|0|0|0|0|0|0|0|0|0|0|0|0|0|0|0|0|0|0|0|0|0|0|0|0|0|0|0|0|0|0|0|0|0|0|0|0|0|0|0|0|0|0|0|0|0|0|0|0|0|0|0|0|0|0|0|0|0|0|0|0|0|0|0|0|0|0|0|0|0|0|0|0|0|0|0|0|0|0|0|0|0|0|0|0|0|0|0|0|0|0|0|0|0|0|0|0|0|0|0|0|0|0|0|0|0|0|0|0|0|0|0|0|0|0|0|0|0|0|0|0|0|0|0|0|0|0|0|0|0|0|0|0|0|0|0|0|0|0|0|0|0|0|0|0|0|0|0|0|0|0|0|0|0|0|0|0|0|0|0|0|0|0|0|0|0|0|0|0|0|0|0|0|0|0|0|0|0|0|0|0|0|0|0|0|0|0|0|0|0|0|0|0|0|0|0|0|0|0|0|0|0|0|0|0|0|0|0|0|0|0|0|0|0|0|0|0|0|0|0|0|0|0|0|0|0|0|0|0|0|0|0|0|0|0|0|0|0|0|0|0|0|0|0|0|0|0|0|0|0|0|0|0|0|0|0|0|0|0|0|0|0|0|0|0|0|0|0|0|0|0|0|0|0|0|0|0|0|0|0|0|0|0|0|0|0|0|0|0|0|0|0|0|0|0|0|0|0|0|0|0|0|0|0|0|0|0|0|0|0|0|0|0|0|0|0|0|0|0|0|0|0|0|0|0|0|0|0|0|0|0|0|223|577|573|520|458|666|545|650|916|990|1153|1368|1540|1850|1462|1432|1598|1417|1498|1659|1330|1513|1397|1317|1304|1273|1173|1262|1062|1049|1080|1090|965|775|709|317</HistCounts>
      </HistItem>
    </Histograms>
    <Metadata>
      <MDI key="ASPECT_FILE">Aspect.asc</MDI>
      <MDI key="ASPECT_MAX">359</MDI>
      <MDI key="ASPECT_MIN">0</MDI>
      <MDI key="ASPECT_NUM_CLASSES">-1</MDI>
      <MDI key="ASPECT_UNIT">2</MDI>
      <MDI key="ASPECT_UNIT_NAME">Azimuth degrees</MDI>
      <MDI key="STATISTICS_MAXIMUM">359</MDI>
      <MDI key="STATISTICS_MEAN">-124,09580568424</MDI>
      <MDI key="STATISTICS_MINIMUM">-9999</MDI>
      <MDI key="STATISTICS_STDDEV">1758,1303102419</MDI>
    </Metadata>
  </PAMRasterBand>
  <PAMRasterBand band="4">
    <Description>Fuel models</Description>
    <Metadata>
      <MDI key="FUEL_MODEL_FILE">fuel.asc</MDI>
      <MDI key="FUEL_MODEL_MAX">22</MDI>
      <MDI key="FUEL_MODEL_MIN">0</MDI>
      <MDI key="FUEL_MODEL_NUM_CLASSES">9</MDI>
      <MDI key="FUEL_MODEL_OPTION">0</MDI>
      <MDI key="FUEL_MODEL_OPTION_DESC">no custom models AND no conversion file needed</MDI>
      <MDI key="FUEL_MODEL_VALUES">0,0,1,2,4,5,9,10,21,22</MDI>
    </Metadata>
  </PAMRasterBand>
  <PAMRasterBand band="5">
    <Description>Canopy cover</Description>
    <Metadata>
      <MDI key="CANOPY_COV_FILE">Cover.asc</MDI>
      <MDI key="CANOPY_COV_MAX">25</MDI>
      <MDI key="CANOPY_COV_MIN">25</MDI>
      <MDI key="CANOPY_COV_NUM_CLASSES">1</MDI>
      <MDI key="CANOPY_COV_UNIT">1</MDI>
      <MDI key="CANOPY_COV_UNIT_NAME">Percent</MDI>
    </Metadata>
  </PAMRasterBand>
</PAMDataset>
